workplan/__init__.py
workplan/ai.py
workplan/cli.py
workplan/git_utils.py
workplan/prompts.py
workplan/storage.py
workplan_ai-0.2.2.dist-info/licenses/LICENSE
workplan_ai-0.2.2.dist-info/METADATA
workplan_ai-0.2.2.dist-info/WHEEL
workplan_ai-0.2.2.dist-info/entry_points.txt
workplan_ai-0.2.2.dist-info/top_level.txt
workplan_ai-0.2.2.dist-info/RECORD
