Metadata-Version: 2.4
Name: workplan-ai
Version: 0.2.2
Summary: AI-powered weekly planning for professional developers
Author-email: Sahil Selokar <sahilselokar03@gmail.com>
License: MIT
Project-URL: Homepage, https://github.com/SahilSelokar/workplan-ai
Project-URL: Bug Tracker, https://github.com/SahilSelokar/workplan-ai/issues
Project-URL: Repository, https://github.com/SahilSelokar/workplan-ai
License-File: LICENSE
Requires-Dist: typer[all]
Requires-Dist: pydantic
Requires-Dist: rich
Requires-Dist: python-dotenv
Requires-Dist: groq
Requires-Dist: keyring
Dynamic: license-file
